rhf/__init__.py
rhf/rhf.py
rhf-0.0.1.dist-info/AUTHORS.rst
rhf-0.0.1.dist-info/LICENSE
rhf-0.0.1.dist-info/METADATA
rhf-0.0.1.dist-info/WHEEL
rhf-0.0.1.dist-info/top_level.txt
rhf-0.0.1.dist-info/RECORD
