Metadata-Version: 2.1
Name: rhf
Version: 0.0.1
Summary: Python implementation of Random Histogram Forest (RHF)
Home-page: https://github.com/anrputina/rhf
Author: Andrian Putina
Author-email: anr.putina@gmail.com
License: MIT license
Keywords: rhf
Platform: UNKNOWN
Classifier: Development Status :: 2 - Pre-Alpha
Classifier: Intended Audience :: Developers
Classifier: License :: OSI Approved :: MIT License
Classifier: Natural Language :: English
Classifier: Programming Language :: Python :: 3
Classifier: Programming Language :: Python :: 3.5
Classifier: Programming Language :: Python :: 3.6
Classifier: Programming Language :: Python :: 3.7
Classifier: Programming Language :: Python :: 3.8
Requires-Python: >=3.5
Requires-Dist: scipy
Requires-Dist: numpy
Requires-Dist: pandas
